{
  "params": {
    "circuits": "OPENQASM 2.0;\ninclude \"qelib1.inc\";\nqreg q[11];\nh q[5];\ncx q[3],q[8];\nh q[8];\ncx q[9],q[4];\ns q[8];\ncx q[7],q[10];\nh q[8];\ncx q[7],q[10];\nx q[4];\ncx q[7],q[8];\nh q[6];\ncx q[8],q[4];\ns q[6];\ncx q[3],q[1];\nx q[7];\ncx q[8],q[4];\nz q[3];\ncx q[8],q[4];\nz q[2];\ncx q[1],q[9];\ns q[0];\ncx q[10],q[7];\nh q[2];\ncx q[10],q[0];\nh q[9];\ncx q[1],q[9];\ns q[6];\ncx q[9],q[1];\nz q[10];\ncx q[9],q[6];\ns q[6];\ncx q[0],q[5];\nz q[9];\ncx q[5],q[0];\nx q[2];\ncx q[8],q[4];\nx q[10];\ncx q[7],q[6];\ns q[9];\ncx q[7],q[8];",
    "observable": "ZIIIIIIIIII",
    "shots": 5000,
    "backends": [
      [
        "ibm_aer",
        "aer.fake_sherbrooke"
      ]
    ],
    "operation": "cc_qubit_prop",
    "perf_exp_val": 0.0,
    "shots_allocation": "qubit_driven_proportional",
    "gate2q_alpha": 0.8
  },
  "results": {
    "ibm_aer": {
      "aer.fake_sherbrooke": {
        "('06635e40a4fa544cb95a53bfdf7d73be', 'ZIIIIIIIIII')": 0.013411018521206944
      }
    }
  },
  "times": {
    "time_total": 11.45843867957592,
    "time_cutting": 0.00012207776308059692,
    "time_execution": 11.457029834389687,
    "time_sew": 0.0012826770544052124
  },
  "stats": {
    "circuit_stats": {
      "qubits": 11,
      "depth": 10,
      "num_gates": 40,
      "2q_depth": 8,
      "num_1q_gates": 20,
      "num_2q_gates": 20,
      "num_measurements": 0,
      "gates": {
        "cx": 20,
        "h": 6,
        "s": 6,
        "x": 4,
        "z": 4
      }
    },
    "cut_info": {
      "num_fragments": 2,
      "fragments_qubits": [
        3,
        8
      ],
      "num_variations": 7,
      "variations": [
        4,
        3
      ]
    },
    "cut_statistics": {
      "num_fragments": 2,
      "num_variants": 8,
      "variations_per_fragment": [
        4,
        3
      ],
      "total_allocated_shots": 5000,
      "total_executed_shots": 5000,
      "min_allocated_shots_per_variant": 341,
      "max_allocated_shots_per_variant": 909,
      "min_executed_shots_per_variant": 341,
      "max_executed_shots_per_variant": 909,
      "shots_per_variant": [
        {
          "variant_index": 0,
          "variant_key": "('60fc0406cc0082df01b2f2dcd2bd8c48', 'IZI')",
          "fragment_hash": "60fc0406cc0082df01b2f2dcd2bd8c48",
          "observable": "IZI",
          "allocated_shots": 341,
          "executed_shots": 341
        },
        {
          "variant_index": 1,
          "variant_key": "('fd862edb2c253d22575a5a93a92bd1d6', 'IZI')",
          "fragment_hash": "fd862edb2c253d22575a5a93a92bd1d6",
          "observable": "IZI",
          "allocated_shots": 341,
          "executed_shots": 341
        },
        {
          "variant_index": 2,
          "variant_key": "('fcdbb4702dab8fb507ac889c43aa91ed', 'IZI')",
          "fragment_hash": "fcdbb4702dab8fb507ac889c43aa91ed",
          "observable": "IZI",
          "allocated_shots": 341,
          "executed_shots": 341
        },
        {
          "variant_index": 3,
          "variant_key": "('3d71dca54ba074a42cbf950ba8c94db1', 'IZI')",
          "fragment_hash": "3d71dca54ba074a42cbf950ba8c94db1",
          "observable": "IZI",
          "allocated_shots": 341,
          "executed_shots": 341
        },
        {
          "variant_index": 4,
          "variant_key": "('f8d92ff6e5d017bb0d1c037950f6768d', 'IIIIIIII')",
          "fragment_hash": "f8d92ff6e5d017bb0d1c037950f6768d",
          "observable": "IIIIIIII",
          "allocated_shots": 909,
          "executed_shots": 909
        },
        {
          "variant_index": 4,
          "variant_key": "('f8d92ff6e5d017bb0d1c037950f6768d', 'IIIIIZII')",
          "fragment_hash": "f8d92ff6e5d017bb0d1c037950f6768d",
          "observable": "IIIIIZII",
          "allocated_shots": 909,
          "executed_shots": 909
        },
        {
          "variant_index": 5,
          "variant_key": "('f8d92ff6e5d017bb0d1c037950f6768d', 'IIIIIXII')",
          "fragment_hash": "f8d92ff6e5d017bb0d1c037950f6768d",
          "observable": "IIIIIXII",
          "allocated_shots": 909,
          "executed_shots": 909
        },
        {
          "variant_index": 6,
          "variant_key": "('f8d92ff6e5d017bb0d1c037950f6768d', 'IIIIIYII')",
          "fragment_hash": "f8d92ff6e5d017bb0d1c037950f6768d",
          "observable": "IIIIIYII",
          "allocated_shots": 909,
          "executed_shots": 909
        }
      ]
    },
    "cut_output": [
      {
        "fragment_hash": "60fc0406cc0082df01b2f2dcd2bd8c48",
        "observables": [
          "IZI",
          "IZI",
          "IZI",
          "IZI"
        ],
        "fragment_stats": {
          "qubits": 3,
          "depth": 4,
          "num_gates": 8,
          "2q_depth": 3,
          "num_1q_gates": 5,
          "num_2q_gates": 3,
          "num_measurements": 0,
          "gates": {
            "cx": 3,
            "h": 1,
            "s": 1,
            "id": 1,
            "z": 1,
            "x": 1
          }
        }
      },
      {
        "fragment_hash": "f8d92ff6e5d017bb0d1c037950f6768d",
        "observables": [
          "IIIIIIII",
          "IIIIIXII",
          "IIIIIYII"
        ],
        "fragment_stats": {
          "qubits": 8,
          "depth": 10,
          "num_gates": 30,
          "2q_depth": 8,
          "num_1q_gates": 13,
          "num_2q_gates": 17,
          "num_measurements": 0,
          "gates": {
            "cx": 17,
            "s": 5,
            "h": 4,
            "x": 2,
            "z": 2
          }
        }
      }
    ],
    "variant_counts": {
      "('60fc0406cc0082df01b2f2dcd2bd8c48', 'IZI')": {
        "000": 5,
        "101": 9,
        "110": 8,
        "100": 159,
        "011": 2,
        "111": 158
      },
      "('fd862edb2c253d22575a5a93a92bd1d6', 'IZI')": {
        "101": 4,
        "110": 6,
        "011": 7,
        "001": 158,
        "000": 7,
        "010": 159
      },
      "('fcdbb4702dab8fb507ac889c43aa91ed', 'IZI')": {
        "101": 10,
        "011": 6,
        "111": 72,
        "100": 72,
        "001": 76,
        "110": 6,
        "000": 10,
        "010": 89
      },
      "('3d71dca54ba074a42cbf950ba8c94db1', 'IZI')": {
        "110": 5,
        "101": 6,
        "100": 79,
        "000": 7,
        "010": 85,
        "011": 9,
        "111": 74,
        "001": 76
      },
      "('f8d92ff6e5d017bb0d1c037950f6768d', 'IIIIIIII')": {
        "10111100": 3,
        "00011100": 6,
        "01011110": 1,
        "10010110": 1,
        "00010000": 1,
        "01011011": 2,
        "10111110": 4,
        "11011101": 3,
        "01010010": 3,
        "11011001": 1,
        "11010100": 2,
        "00011110": 5,
        "01011010": 103,
        "00001011": 1,
        "01111010": 5,
        "10001110": 3,
        "01011001": 3,
        "00001000": 1,
        "10011100": 83,
        "00011011": 2,
        "01010000": 4,
        "00011010": 103,
        "01011000": 108,
        "00111010": 1,
        "10001100": 1,
        "11011110": 96,
        "11011100": 99,
        "01111101": 1,
        "10010100": 1,
        "11111110": 4,
        "10011110": 102,
        "11001110": 5,
        "00001010": 2,
        "11011111": 4,
        "01011100": 3,
        "11011010": 4,
        "10011111": 2,
        "11111100": 2,
        "00001001": 1,
        "01111000": 3,
        "11001100": 1,
        "00111000": 6,
        "10000110": 1,
        "00011001": 2,
        "01001000": 1,
        "10011101": 3,
        "00011000": 106,
        "10011010": 4,
        "11011000": 4,
        "10011000": 2
      },
      "('f8d92ff6e5d017bb0d1c037950f6768d', 'IIIIIZII')": {
        "00011001": 1,
        "01011110": 2,
        "10011101": 3,
        "00001010": 2,
        "01011011": 1,
        "11110100": 1,
        "01011001": 2,
        "01010110": 1,
        "10001110": 1,
        "01111010": 1,
        "01111000": 4,
        "11010110": 2,
        "11011110": 85,
        "11011100": 96,
        "00111010": 5,
        "10001100": 2,
        "11011010": 1,
        "11011111": 1,
        "01011100": 4,
        "01011010": 107,
        "00011010": 99,
        "01011000": 103,
        "10010100": 3,
        "11111110": 4,
        "10011110": 128,
        "00011110": 2,
        "11010100": 4,
        "10011010": 2,
        "00011000": 99,
        "11011000": 5,
        "01001010": 1,
        "00010010": 1,
        "00011100": 6,
        "10111100": 3,
        "00010000": 2,
        "01010000": 1,
        "00011011": 3,
        "10111110": 3,
        "11001100": 1,
        "00111000": 3,
        "11111101": 1,
        "10011100": 103,
        "00001000": 4,
        "10011111": 2,
        "11111100": 4
      },
      "('f8d92ff6e5d017bb0d1c037950f6768d', 'IIIIIXII')": {
        "00111110": 1,
        "00011011": 1,
        "01011100": 2,
        "11011010": 1,
        "11101100": 1,
        "10011101": 4,
        "11011000": 4,
        "01111110": 3,
        "01111010": 58,
        "00111010": 47,
        "01001011": 1,
        "11110100": 1,
        "10010100": 1,
        "10011110": 44,
        "10111100": 58,
        "11111010": 2,
        "01010010": 1,
        "01011110": 4,
        "00011000": 50,
        "00111011": 2,
        "00101000": 1,
        "00011001": 2,
        "10011010": 3,
        "10011011": 1,
        "00101010": 1,
        "00111000": 46,
        "10111110": 62,
        "11111110": 49,
        "01101000": 1,
        "00111100": 4,
        "10011100": 59,
        "00001000": 1,
        "01110000": 1,
        "01011000": 44,
        "01001000": 1,
        "00011010": 50,
        "11111100": 52,
        "11011110": 50,
        "11011100": 56,
        "10111111": 3,
        "01010000": 1,
        "01011010": 53,
        "11111011": 1,
        "10111101": 1,
        "01111000": 51,
        "11111111": 1,
        "11001110": 1,
        "11111001": 1,
        "00110000": 2,
        "00010010": 1,
        "01001010": 2,
        "01011001": 5,
        "00011100": 3,
        "00110010": 2,
        "10111000": 1,
        "11011111": 3,
        "01110010": 1,
        "11011101": 1,
        "11010100": 2,
        "00011110": 1,
        "00001010": 1,
        "00111001": 1
      },
      "('f8d92ff6e5d017bb0d1c037950f6768d', 'IIIIIYII')": {
        "00010110": 1,
        "00111100": 2,
        "11111010": 1,
        "00111111": 1,
        "01010010": 1,
        "01011001": 6,
        "11011010": 2,
        "11101100": 1,
        "01111011": 2,
        "00111000": 57,
        "11111101": 2,
        "10111110": 43,
        "11110100": 2,
        "11111110": 47,
        "10010100": 2,
        "10011100": 52,
        "11110110": 1,
        "00001000": 1,
        "10111100": 44,
        "01111010": 54,
        "00111010": 65,
        "00011011": 1,
        "01010000": 1,
        "00111001": 2,
        "11011110": 52,
        "11011100": 40,
        "11111000": 3,
        "01011111": 1,
        "11010110": 2,
        "10101110": 3,
        "10010110": 1,
        "11111100": 41,
        "10011111": 2,
        "00111011": 3,
        "00011000": 51,
        "10011010": 2,
        "01011010": 64,
        "11011101": 4,
        "01011000": 59,
        "11111111": 1,
        "01111000": 53,
        "11011111": 1,
        "01110010": 1,
        "00000010": 1,
        "00010010": 3,
        "00111110": 2,
        "00010001": 1,
        "10111101": 2,
        "10001100": 1,
        "10111010": 2,
        "00011110": 3,
        "00011010": 67,
        "01001000": 1,
        "10011101": 1,
        "00011100": 3,
        "00110010": 1,
        "01111110": 2,
        "10101100": 2,
        "10011110": 39,
        "10011000": 1,
        "01111001": 1,
        "00011001": 1
      }
    },
    "variant_exp_values": {
      "('60fc0406cc0082df01b2f2dcd2bd8c48', 'IZI')": 0.014662756598240456,
      "('fd862edb2c253d22575a5a93a92bd1d6', 'IZI')": -0.008797653958944274,
      "('fcdbb4702dab8fb507ac889c43aa91ed', 'IZI')": -0.014662756598240484,
      "('3d71dca54ba074a42cbf950ba8c94db1', 'IZI')": -0.014662756598240484,
      "('f8d92ff6e5d017bb0d1c037950f6768d', 'IIIIIIII')": [
        0.9999999999999999,
        0.9361936193619358
      ],
      "('f8d92ff6e5d017bb0d1c037950f6768d', 'IIIIIXII')": -0.0011001100110010602,
      "('f8d92ff6e5d017bb0d1c037950f6768d', 'IIIIIYII')": 0.029702970297029705
    },
    "variant_shots_budget": {
      "('60fc0406cc0082df01b2f2dcd2bd8c48', 'IZI')": 341,
      "('fd862edb2c253d22575a5a93a92bd1d6', 'IZI')": 341,
      "('fcdbb4702dab8fb507ac889c43aa91ed', 'IZI')": 341,
      "('3d71dca54ba074a42cbf950ba8c94db1', 'IZI')": 341,
      "('f8d92ff6e5d017bb0d1c037950f6768d', 'IIIIIIII')": 909,
      "('f8d92ff6e5d017bb0d1c037950f6768d', 'IIIIIZII')": 909,
      "('f8d92ff6e5d017bb0d1c037950f6768d', 'IIIIIXII')": 909,
      "('f8d92ff6e5d017bb0d1c037950f6768d', 'IIIIIYII')": 909
    },
    "variant_shots_executed": {
      "('60fc0406cc0082df01b2f2dcd2bd8c48', 'IZI')": 341,
      "('fd862edb2c253d22575a5a93a92bd1d6', 'IZI')": 341,
      "('fcdbb4702dab8fb507ac889c43aa91ed', 'IZI')": 341,
      "('3d71dca54ba074a42cbf950ba8c94db1', 'IZI')": 341,
      "('f8d92ff6e5d017bb0d1c037950f6768d', 'IIIIIIII')": 909,
      "('f8d92ff6e5d017bb0d1c037950f6768d', 'IIIIIZII')": 909,
      "('f8d92ff6e5d017bb0d1c037950f6768d', 'IIIIIXII')": 909,
      "('f8d92ff6e5d017bb0d1c037950f6768d', 'IIIIIYII')": 909
    }
  },
  "absolute_error": {
    "ibm_aer": {
      "aer.fake_sherbrooke": {
        "('06635e40a4fa544cb95a53bfdf7d73be', 'ZIIIIIIIIII')": 0.013411018521206944
      }
    }
  },
  "shots_executed": 5000,
  "distance_to_noisy_vanilla": 0.01661101852120699
}