{
  "params": {
    "circuits": "OPENQASM 2.0;\ninclude \"qelib1.inc\";\nqreg q[5];\nx q[4];\ncx q[1],q[0];\ns q[4];\ncx q[4],q[2];\nh q[1];\ncx q[4],q[2];\nh q[3];\ncx q[1],q[4];\nt q[4];\ncx q[1],q[3];\nt q[0];\ncx q[0],q[1];\nh q[4];\ncx q[3],q[0];\nh q[2];\ncx q[1],q[3];\nt q[0];\ncx q[1],q[4];\nt q[3];\ncx q[0],q[4];\nh q[4];\ncx q[0],q[3];\nz q[2];\ncx q[1],q[0];\nh q[2];\ncx q[3],q[0];\nz q[2];\ncx q[4],q[2];\nh q[4];\ncx q[2],q[4];\nt q[0];\ncx q[0],q[3];\nx q[3];\ncx q[1],q[3];\nt q[1];\ncx q[1],q[0];\ns q[2];\ncx q[0],q[3];\ns q[4];\ncx q[2],q[4];",
    "observable": "ZIIII",
    "shots": 30000,
    "backends": [
      [
        "ibm_aer",
        "aer.fake_torino"
      ]
    ],
    "operation": "cc_incremental_qubit_prop",
    "perf_exp_val": 0.0,
    "shots_allocation": "qubit_driven_proportional_incremental",
    "incremental_batch_shots": 50,
    "incremental_threshold": 0.01,
    "incremental_offset": 3,
    "incremental_stability_k": 3,
    "incremental_stopping_criterion": "ewma",
    "incremental_distance_metric": "tvd",
    "incremental_window_size": 3,
    "incremental_ewma_alpha": 0.5,
    "gate2q_alpha": 0.8
  },
  "results": {
    "ibm_aer": {
      "aer.fake_torino": {
        "('3364928460a7f13fdc149fc981b2a466', 'ZIIII')": -0.030400000000000073
      }
    }
  },
  "times": {
    "time_total": 640.0711991302669,
    "time_cutting": 0.00011551007628440857,
    "time_execution": 640.0700087058358,
    "time_sew": 0.0010694130323827267
  },
  "stats": {
    "circuit_stats": {
      "qubits": 5,
      "depth": 21,
      "num_gates": 40,
      "2q_depth": 16,
      "num_1q_gates": 20,
      "num_2q_gates": 20,
      "num_measurements": 0,
      "gates": {
        "cx": 20,
        "h": 7,
        "t": 6,
        "s": 3,
        "x": 2,
        "z": 2
      }
    },
    "cut_info": {
      "num_fragments": 2,
      "fragments_qubits": [
        3,
        4
      ],
      "num_variations": 24,
      "variations": [
        12,
        12
      ]
    },
    "cut_statistics": {
      "num_fragments": 2,
      "num_variants": 32,
      "variations_per_fragment": [
        12,
        12
      ],
      "total_allocated_shots": 30000,
      "total_executed_shots": 12800,
      "min_allocated_shots_per_variant": 804,
      "max_allocated_shots_per_variant": 1071,
      "min_executed_shots_per_variant": 400,
      "max_executed_shots_per_variant": 400,
      "shots_per_variant": [
        {
          "variant_index": 0,
          "variant_key": "('7a1cf0d19d9af24d16b163b3becc2b5b', 'III')",
          "fragment_hash": "7a1cf0d19d9af24d16b163b3becc2b5b",
          "observable": "III",
          "allocated_shots": 804,
          "executed_shots": 400,
          "iterations": 8
        },
        {
          "variant_index": 0,
          "variant_key": "('7a1cf0d19d9af24d16b163b3becc2b5b', 'ZII')",
          "fragment_hash": "7a1cf0d19d9af24d16b163b3becc2b5b",
          "observable": "ZII",
          "allocated_shots": 804,
          "executed_shots": 400,
          "iterations": 8
        },
        {
          "variant_index": 1,
          "variant_key": "('7a1cf0d19d9af24d16b163b3becc2b5b', 'XII')",
          "fragment_hash": "7a1cf0d19d9af24d16b163b3becc2b5b",
          "observable": "XII",
          "allocated_shots": 804,
          "executed_shots": 400,
          "iterations": 8
        },
        {
          "variant_index": 2,
          "variant_key": "('7a1cf0d19d9af24d16b163b3becc2b5b', 'YII')",
          "fragment_hash": "7a1cf0d19d9af24d16b163b3becc2b5b",
          "observable": "YII",
          "allocated_shots": 804,
          "executed_shots": 400,
          "iterations": 8
        },
        {
          "variant_index": 3,
          "variant_key": "('92a20c78bff5d88011eb51048df8311f', 'III')",
          "fragment_hash": "92a20c78bff5d88011eb51048df8311f",
          "observable": "III",
          "allocated_shots": 804,
          "executed_shots": 400,
          "iterations": 8
        },
        {
          "variant_index": 3,
          "variant_key": "('92a20c78bff5d88011eb51048df8311f', 'ZII')",
          "fragment_hash": "92a20c78bff5d88011eb51048df8311f",
          "observable": "ZII",
          "allocated_shots": 804,
          "executed_shots": 400,
          "iterations": 8
        },
        {
          "variant_index": 4,
          "variant_key": "('92a20c78bff5d88011eb51048df8311f', 'XII')",
          "fragment_hash": "92a20c78bff5d88011eb51048df8311f",
          "observable": "XII",
          "allocated_shots": 804,
          "executed_shots": 400,
          "iterations": 8
        },
        {
          "variant_index": 5,
          "variant_key": "('92a20c78bff5d88011eb51048df8311f', 'YII')",
          "fragment_hash": "92a20c78bff5d88011eb51048df8311f",
          "observable": "YII",
          "allocated_shots": 804,
          "executed_shots": 400,
          "iterations": 8
        },
        {
          "variant_index": 6,
          "variant_key": "('f2f288fe99730e84d15df38b099cd208', 'III')",
          "fragment_hash": "f2f288fe99730e84d15df38b099cd208",
          "observable": "III",
          "allocated_shots": 804,
          "executed_shots": 400,
          "iterations": 8
        },
        {
          "variant_index": 6,
          "variant_key": "('f2f288fe99730e84d15df38b099cd208', 'ZII')",
          "fragment_hash": "f2f288fe99730e84d15df38b099cd208",
          "observable": "ZII",
          "allocated_shots": 804,
          "executed_shots": 400,
          "iterations": 8
        },
        {
          "variant_index": 7,
          "variant_key": "('f2f288fe99730e84d15df38b099cd208', 'XII')",
          "fragment_hash": "f2f288fe99730e84d15df38b099cd208",
          "observable": "XII",
          "allocated_shots": 804,
          "executed_shots": 400,
          "iterations": 8
        },
        {
          "variant_index": 8,
          "variant_key": "('f2f288fe99730e84d15df38b099cd208', 'YII')",
          "fragment_hash": "f2f288fe99730e84d15df38b099cd208",
          "observable": "YII",
          "allocated_shots": 804,
          "executed_shots": 400,
          "iterations": 8
        },
        {
          "variant_index": 9,
          "variant_key": "('1011244113be3680b3d3e6b617b27dae', 'III')",
          "fragment_hash": "1011244113be3680b3d3e6b617b27dae",
          "observable": "III",
          "allocated_shots": 804,
          "executed_shots": 400,
          "iterations": 8
        },
        {
          "variant_index": 9,
          "variant_key": "('1011244113be3680b3d3e6b617b27dae', 'ZII')",
          "fragment_hash": "1011244113be3680b3d3e6b617b27dae",
          "observable": "ZII",
          "allocated_shots": 804,
          "executed_shots": 400,
          "iterations": 8
        },
        {
          "variant_index": 10,
          "variant_key": "('1011244113be3680b3d3e6b617b27dae', 'XII')",
          "fragment_hash": "1011244113be3680b3d3e6b617b27dae",
          "observable": "XII",
          "allocated_shots": 804,
          "executed_shots": 400,
          "iterations": 8
        },
        {
          "variant_index": 11,
          "variant_key": "('1011244113be3680b3d3e6b617b27dae', 'YII')",
          "fragment_hash": "1011244113be3680b3d3e6b617b27dae",
          "observable": "YII",
          "allocated_shots": 804,
          "executed_shots": 400,
          "iterations": 8
        },
        {
          "variant_index": 12,
          "variant_key": "('00cb36ab40c912315350663a5775a661', 'IZII')",
          "fragment_hash": "00cb36ab40c912315350663a5775a661",
          "observable": "IZII",
          "allocated_shots": 1071,
          "executed_shots": 400,
          "iterations": 8
        },
        {
          "variant_index": 12,
          "variant_key": "('00cb36ab40c912315350663a5775a661', 'IZZI')",
          "fragment_hash": "00cb36ab40c912315350663a5775a661",
          "observable": "IZZI",
          "allocated_shots": 1071,
          "executed_shots": 400,
          "iterations": 8
        },
        {
          "variant_index": 13,
          "variant_key": "('00cb36ab40c912315350663a5775a661', 'IZXI')",
          "fragment_hash": "00cb36ab40c912315350663a5775a661",
          "observable": "IZXI",
          "allocated_shots": 1071,
          "executed_shots": 400,
          "iterations": 8
        },
        {
          "variant_index": 14,
          "variant_key": "('00cb36ab40c912315350663a5775a661', 'IZYI')",
          "fragment_hash": "00cb36ab40c912315350663a5775a661",
          "observable": "IZYI",
          "allocated_shots": 1071,
          "executed_shots": 400,
          "iterations": 8
        },
        {
          "variant_index": 15,
          "variant_key": "('1687d8b9ede8d7bd59c825e605d89bc1', 'IZII')",
          "fragment_hash": "1687d8b9ede8d7bd59c825e605d89bc1",
          "observable": "IZII",
          "allocated_shots": 1071,
          "executed_shots": 400,
          "iterations": 8
        },
        {
          "variant_index": 15,
          "variant_key": "('1687d8b9ede8d7bd59c825e605d89bc1', 'IZZI')",
          "fragment_hash": "1687d8b9ede8d7bd59c825e605d89bc1",
          "observable": "IZZI",
          "allocated_shots": 1071,
          "executed_shots": 400,
          "iterations": 8
        },
        {
          "variant_index": 16,
          "variant_key": "('1687d8b9ede8d7bd59c825e605d89bc1', 'IZXI')",
          "fragment_hash": "1687d8b9ede8d7bd59c825e605d89bc1",
          "observable": "IZXI",
          "allocated_shots": 1071,
          "executed_shots": 400,
          "iterations": 8
        },
        {
          "variant_index": 17,
          "variant_key": "('1687d8b9ede8d7bd59c825e605d89bc1', 'IZYI')",
          "fragment_hash": "1687d8b9ede8d7bd59c825e605d89bc1",
          "observable": "IZYI",
          "allocated_shots": 1071,
          "executed_shots": 400,
          "iterations": 8
        },
        {
          "variant_index": 18,
          "variant_key": "('da6f6010ba2f1879dba5e0b8e9abf52c', 'IZII')",
          "fragment_hash": "da6f6010ba2f1879dba5e0b8e9abf52c",
          "observable": "IZII",
          "allocated_shots": 1071,
          "executed_shots": 400,
          "iterations": 8
        },
        {
          "variant_index": 18,
          "variant_key": "('da6f6010ba2f1879dba5e0b8e9abf52c', 'IZZI')",
          "fragment_hash": "da6f6010ba2f1879dba5e0b8e9abf52c",
          "observable": "IZZI",
          "allocated_shots": 1071,
          "executed_shots": 400,
          "iterations": 8
        },
        {
          "variant_index": 19,
          "variant_key": "('da6f6010ba2f1879dba5e0b8e9abf52c', 'IZXI')",
          "fragment_hash": "da6f6010ba2f1879dba5e0b8e9abf52c",
          "observable": "IZXI",
          "allocated_shots": 1071,
          "executed_shots": 400,
          "iterations": 8
        },
        {
          "variant_index": 20,
          "variant_key": "('da6f6010ba2f1879dba5e0b8e9abf52c', 'IZYI')",
          "fragment_hash": "da6f6010ba2f1879dba5e0b8e9abf52c",
          "observable": "IZYI",
          "allocated_shots": 1071,
          "executed_shots": 400,
          "iterations": 8
        },
        {
          "variant_index": 21,
          "variant_key": "('41583aeef03cd201c7c8775e4113986e', 'IZII')",
          "fragment_hash": "41583aeef03cd201c7c8775e4113986e",
          "observable": "IZII",
          "allocated_shots": 1071,
          "executed_shots": 400,
          "iterations": 8
        },
        {
          "variant_index": 21,
          "variant_key": "('41583aeef03cd201c7c8775e4113986e', 'IZZI')",
          "fragment_hash": "41583aeef03cd201c7c8775e4113986e",
          "observable": "IZZI",
          "allocated_shots": 1071,
          "executed_shots": 400,
          "iterations": 8
        },
        {
          "variant_index": 22,
          "variant_key": "('41583aeef03cd201c7c8775e4113986e', 'IZXI')",
          "fragment_hash": "41583aeef03cd201c7c8775e4113986e",
          "observable": "IZXI",
          "allocated_shots": 1071,
          "executed_shots": 400,
          "iterations": 8
        },
        {
          "variant_index": 23,
          "variant_key": "('41583aeef03cd201c7c8775e4113986e', 'IZYI')",
          "fragment_hash": "41583aeef03cd201c7c8775e4113986e",
          "observable": "IZYI",
          "allocated_shots": 1071,
          "executed_shots": 400,
          "iterations": 8
        }
      ]
    },
    "cut_output": [
      {
        "fragment_hash": "7a1cf0d19d9af24d16b163b3becc2b5b",
        "observables": [
          "III",
          "XII",
          "YII",
          "III",
          "XII",
          "YII",
          "III",
          "XII",
          "YII",
          "III",
          "XII",
          "YII"
        ],
        "fragment_stats": {
          "qubits": 3,
          "depth": 13,
          "num_gates": 16,
          "2q_depth": 5,
          "num_1q_gates": 11,
          "num_2q_gates": 5,
          "num_measurements": 0,
          "gates": {
            "cx": 5,
            "h": 4,
            "s": 3,
            "z": 2,
            "x": 1,
            "id": 1
          }
        }
      },
      {
        "fragment_hash": "00cb36ab40c912315350663a5775a661",
        "observables": [
          "IZII",
          "IZXI",
          "IZYI",
          "IZII",
          "IZXI",
          "IZYI",
          "IZII",
          "IZXI",
          "IZYI",
          "IZII",
          "IZXI",
          "IZYI"
        ],
        "fragment_stats": {
          "qubits": 4,
          "depth": 19,
          "num_gates": 26,
          "2q_depth": 15,
          "num_1q_gates": 11,
          "num_2q_gates": 15,
          "num_measurements": 0,
          "gates": {
            "cx": 15,
            "t": 6,
            "h": 3,
            "id": 1,
            "x": 1
          }
        }
      }
    ],
    "variant_counts": {
      "('7a1cf0d19d9af24d16b163b3becc2b5b', 'III')": {
        "010": 8,
        "100": 32,
        "001": 104,
        "101": 72,
        "111": 80,
        "011": 104
      },
      "('7a1cf0d19d9af24d16b163b3becc2b5b', 'ZII')": {
        "010": 8,
        "100": 32,
        "001": 104,
        "101": 72,
        "111": 80,
        "011": 104
      },
      "('7a1cf0d19d9af24d16b163b3becc2b5b', 'XII')": {
        "110": 48,
        "010": 40,
        "000": 56,
        "001": 48,
        "100": 64,
        "101": 40,
        "111": 32,
        "011": 72
      },
      "('7a1cf0d19d9af24d16b163b3becc2b5b', 'YII')": {
        "110": 48,
        "010": 40,
        "000": 56,
        "001": 48,
        "100": 64,
        "101": 40,
        "111": 32,
        "011": 72
      },
      "('92a20c78bff5d88011eb51048df8311f', 'III')": {
        "010": 8,
        "100": 32,
        "001": 104,
        "101": 72,
        "111": 80,
        "011": 104
      },
      "('92a20c78bff5d88011eb51048df8311f', 'ZII')": {
        "010": 8,
        "100": 32,
        "001": 104,
        "101": 72,
        "111": 80,
        "011": 104
      },
      "('92a20c78bff5d88011eb51048df8311f', 'XII')": {
        "110": 48,
        "010": 40,
        "000": 56,
        "001": 48,
        "100": 64,
        "101": 40,
        "111": 32,
        "011": 72
      },
      "('92a20c78bff5d88011eb51048df8311f', 'YII')": {
        "110": 48,
        "010": 40,
        "000": 56,
        "001": 48,
        "100": 64,
        "101": 40,
        "111": 32,
        "011": 72
      },
      "('f2f288fe99730e84d15df38b099cd208', 'III')": {
        "001": 8,
        "010": 8,
        "110": 32,
        "111": 152,
        "011": 200
      },
      "('f2f288fe99730e84d15df38b099cd208', 'ZII')": {
        "001": 8,
        "010": 8,
        "110": 32,
        "111": 152,
        "011": 200
      },
      "('f2f288fe99730e84d15df38b099cd208', 'XII')": {
        "000": 8,
        "010": 72,
        "110": 96,
        "111": 88,
        "011": 136
      },
      "('f2f288fe99730e84d15df38b099cd208', 'YII')": {
        "000": 8,
        "010": 72,
        "110": 96,
        "111": 88,
        "011": 136
      },
      "('1011244113be3680b3d3e6b617b27dae', 'III')": {
        "010": 8,
        "100": 32,
        "001": 104,
        "101": 72,
        "111": 80,
        "011": 104
      },
      "('1011244113be3680b3d3e6b617b27dae', 'ZII')": {
        "010": 8,
        "100": 32,
        "001": 104,
        "101": 72,
        "111": 80,
        "011": 104
      },
      "('1011244113be3680b3d3e6b617b27dae', 'XII')": {
        "110": 48,
        "010": 40,
        "000": 56,
        "001": 48,
        "100": 64,
        "101": 40,
        "111": 32,
        "011": 72
      },
      "('1011244113be3680b3d3e6b617b27dae', 'YII')": {
        "110": 48,
        "010": 40,
        "000": 56,
        "001": 48,
        "100": 64,
        "101": 40,
        "111": 32,
        "011": 72
      },
      "('00cb36ab40c912315350663a5775a661', 'IZII')": {
        "0100": 8,
        "0001": 32,
        "1101": 8,
        "0000": 32,
        "1010": 48,
        "1100": 48,
        "1001": 16,
        "1000": 32,
        "0101": 24,
        "1110": 32,
        "1011": 8,
        "0011": 32,
        "0111": 80
      },
      "('00cb36ab40c912315350663a5775a661', 'IZZI')": {
        "0100": 8,
        "0001": 32,
        "1101": 8,
        "0000": 32,
        "1010": 48,
        "1100": 48,
        "1001": 16,
        "1000": 32,
        "0101": 24,
        "1110": 32,
        "1011": 8,
        "0011": 32,
        "0111": 80
      },
      "('00cb36ab40c912315350663a5775a661', 'IZXI')": {
        "0110": 8,
        "1101": 8,
        "1010": 64,
        "0100": 32,
        "1110": 8,
        "0101": 64,
        "1001": 16,
        "1000": 80,
        "1100": 8,
        "1011": 8,
        "0111": 104
      },
      "('00cb36ab40c912315350663a5775a661', 'IZYI')": {
        "0100": 8,
        "0001": 32,
        "1101": 8,
        "0000": 32,
        "1010": 48,
        "1100": 48,
        "1001": 16,
        "1000": 32,
        "0101": 24,
        "1110": 32,
        "1011": 8,
        "0011": 32,
        "0111": 80
      },
      "('1687d8b9ede8d7bd59c825e605d89bc1', 'IZII')": {
        "0100": 8,
        "0001": 32,
        "1101": 8,
        "0000": 32,
        "1010": 48,
        "1100": 48,
        "1001": 16,
        "1000": 32,
        "0101": 24,
        "1110": 32,
        "1011": 8,
        "0011": 32,
        "0111": 80
      },
      "('1687d8b9ede8d7bd59c825e605d89bc1', 'IZZI')": {
        "0100": 8,
        "0001": 32,
        "1101": 8,
        "0000": 32,
        "1010": 48,
        "1100": 48,
        "1001": 16,
        "1000": 32,
        "0101": 24,
        "1110": 32,
        "1011": 8,
        "0011": 32,
        "0111": 80
      },
      "('1687d8b9ede8d7bd59c825e605d89bc1', 'IZXI')": {
        "1101": 16,
        "1110": 72,
        "0010": 8,
        "0000": 32,
        "1111": 8,
        "0001": 64,
        "1001": 8,
        "1100": 88,
        "0011": 104
      },
      "('1687d8b9ede8d7bd59c825e605d89bc1', 'IZYI')": {
        "0100": 8,
        "0001": 32,
        "1101": 8,
        "0000": 32,
        "1010": 48,
        "1100": 48,
        "1001": 16,
        "1000": 32,
        "0101": 24,
        "1110": 32,
        "1011": 8,
        "0011": 32,
        "0111": 80
      },
      "('da6f6010ba2f1879dba5e0b8e9abf52c', 'IZII')": {
        "0100": 8,
        "1101": 8,
        "1110": 40,
        "1010": 24,
        "0000": 32,
        "0001": 64,
        "1001": 24,
        "1000": 56,
        "1100": 40,
        "0111": 104
      },
      "('da6f6010ba2f1879dba5e0b8e9abf52c', 'IZZI')": {
        "0100": 8,
        "1101": 8,
        "1110": 40,
        "1010": 24,
        "0000": 32,
        "0001": 64,
        "1001": 24,
        "1000": 56,
        "1100": 40,
        "0111": 104
      },
      "('da6f6010ba2f1879dba5e0b8e9abf52c', 'IZXI')": {
        "0100": 8,
        "0001": 32,
        "1101": 8,
        "0000": 32,
        "1010": 48,
        "1100": 48,
        "1001": 16,
        "1000": 32,
        "0101": 24,
        "1110": 32,
        "1011": 8,
        "0011": 32,
        "0111": 80
      },
      "('da6f6010ba2f1879dba5e0b8e9abf52c', 'IZYI')": {
        "0100": 8,
        "1110": 8,
        "0111": 16,
        "0011": 56,
        "1011": 16,
        "1010": 72,
        "0000": 8,
        "0010": 24,
        "1100": 72,
        "1000": 8,
        "0101": 88,
        "1001": 8,
        "1101": 8,
        "0001": 8
      },
      "('41583aeef03cd201c7c8775e4113986e', 'IZII')": {
        "0100": 8,
        "1101": 8,
        "1000": 8,
        "1001": 16,
        "1100": 72,
        "0000": 32,
        "0001": 64,
        "1010": 72,
        "1110": 8,
        "1011": 8,
        "0111": 104
      },
      "('41583aeef03cd201c7c8775e4113986e', 'IZZI')": {
        "0100": 8,
        "1101": 8,
        "1000": 8,
        "1001": 16,
        "1100": 72,
        "0000": 32,
        "0001": 64,
        "1010": 72,
        "1110": 8,
        "1011": 8,
        "0111": 104
      },
      "('41583aeef03cd201c7c8775e4113986e', 'IZXI')": {
        "0100": 8,
        "0001": 32,
        "1101": 8,
        "0000": 32,
        "1010": 48,
        "1100": 48,
        "1001": 16,
        "1000": 32,
        "0101": 24,
        "1110": 32,
        "1011": 8,
        "0011": 32,
        "0111": 80
      },
      "('41583aeef03cd201c7c8775e4113986e', 'IZYI')": {
        "0100": 8,
        "1101": 8,
        "1000": 8,
        "1001": 16,
        "1100": 72,
        "0000": 32,
        "0001": 64,
        "1010": 72,
        "1110": 8,
        "1011": 8,
        "0111": 104
      }
    },
    "variant_exp_values": {
      "('7a1cf0d19d9af24d16b163b3becc2b5b', 'III')": [
        1.0,
        -0.8
      ],
      "('7a1cf0d19d9af24d16b163b3becc2b5b', 'XII')": 0.040000000000000036,
      "('7a1cf0d19d9af24d16b163b3becc2b5b', 'YII')": 0.040000000000000036,
      "('92a20c78bff5d88011eb51048df8311f', 'III')": [
        1.0,
        -0.8
      ],
      "('92a20c78bff5d88011eb51048df8311f', 'XII')": 0.040000000000000036,
      "('92a20c78bff5d88011eb51048df8311f', 'YII')": 0.040000000000000036,
      "('f2f288fe99730e84d15df38b099cd208', 'III')": [
        1.0,
        -0.8
      ],
      "('f2f288fe99730e84d15df38b099cd208', 'XII')": -0.12000000000000008,
      "('f2f288fe99730e84d15df38b099cd208', 'YII')": -0.12000000000000008,
      "('1011244113be3680b3d3e6b617b27dae', 'III')": [
        1.0,
        -0.8
      ],
      "('1011244113be3680b3d3e6b617b27dae', 'XII')": 0.040000000000000036,
      "('1011244113be3680b3d3e6b617b27dae', 'YII')": 0.040000000000000036,
      "('00cb36ab40c912315350663a5775a661', 'IZII')": [
        -5.551115123125783e-17,
        0.12000000000000002
      ],
      "('00cb36ab40c912315350663a5775a661', 'IZXI')": 0.08000000000000002,
      "('00cb36ab40c912315350663a5775a661', 'IZYI')": 0.12000000000000002,
      "('1687d8b9ede8d7bd59c825e605d89bc1', 'IZII')": [
        -5.551115123125783e-17,
        0.12000000000000002
      ],
      "('1687d8b9ede8d7bd59c825e605d89bc1', 'IZXI')": -0.07999999999999999,
      "('1687d8b9ede8d7bd59c825e605d89bc1', 'IZYI')": 0.12000000000000002,
      "('da6f6010ba2f1879dba5e0b8e9abf52c', 'IZII')": [
        0.16000000000000003,
        0.6000000000000001
      ],
      "('da6f6010ba2f1879dba5e0b8e9abf52c', 'IZXI')": 0.12000000000000002,
      "('da6f6010ba2f1879dba5e0b8e9abf52c', 'IZYI')": -0.72,
      "('41583aeef03cd201c7c8775e4113986e', 'IZII')": [
        0.03999999999999998,
        0.16000000000000003
      ],
      "('41583aeef03cd201c7c8775e4113986e', 'IZXI')": 0.12000000000000002,
      "('41583aeef03cd201c7c8775e4113986e', 'IZYI')": 0.16000000000000003
    },
    "variant_shots_budget": {
      "('7a1cf0d19d9af24d16b163b3becc2b5b', 'III')": 804,
      "('7a1cf0d19d9af24d16b163b3becc2b5b', 'ZII')": 804,
      "('7a1cf0d19d9af24d16b163b3becc2b5b', 'XII')": 804,
      "('7a1cf0d19d9af24d16b163b3becc2b5b', 'YII')": 804,
      "('92a20c78bff5d88011eb51048df8311f', 'III')": 804,
      "('92a20c78bff5d88011eb51048df8311f', 'ZII')": 804,
      "('92a20c78bff5d88011eb51048df8311f', 'XII')": 804,
      "('92a20c78bff5d88011eb51048df8311f', 'YII')": 804,
      "('f2f288fe99730e84d15df38b099cd208', 'III')": 804,
      "('f2f288fe99730e84d15df38b099cd208', 'ZII')": 804,
      "('f2f288fe99730e84d15df38b099cd208', 'XII')": 804,
      "('f2f288fe99730e84d15df38b099cd208', 'YII')": 804,
      "('1011244113be3680b3d3e6b617b27dae', 'III')": 804,
      "('1011244113be3680b3d3e6b617b27dae', 'ZII')": 804,
      "('1011244113be3680b3d3e6b617b27dae', 'XII')": 804,
      "('1011244113be3680b3d3e6b617b27dae', 'YII')": 804,
      "('00cb36ab40c912315350663a5775a661', 'IZII')": 1071,
      "('00cb36ab40c912315350663a5775a661', 'IZZI')": 1071,
      "('00cb36ab40c912315350663a5775a661', 'IZXI')": 1071,
      "('00cb36ab40c912315350663a5775a661', 'IZYI')": 1071,
      "('1687d8b9ede8d7bd59c825e605d89bc1', 'IZII')": 1071,
      "('1687d8b9ede8d7bd59c825e605d89bc1', 'IZZI')": 1071,
      "('1687d8b9ede8d7bd59c825e605d89bc1', 'IZXI')": 1071,
      "('1687d8b9ede8d7bd59c825e605d89bc1', 'IZYI')": 1071,
      "('da6f6010ba2f1879dba5e0b8e9abf52c', 'IZII')": 1071,
      "('da6f6010ba2f1879dba5e0b8e9abf52c', 'IZZI')": 1071,
      "('da6f6010ba2f1879dba5e0b8e9abf52c', 'IZXI')": 1071,
      "('da6f6010ba2f1879dba5e0b8e9abf52c', 'IZYI')": 1071,
      "('41583aeef03cd201c7c8775e4113986e', 'IZII')": 1071,
      "('41583aeef03cd201c7c8775e4113986e', 'IZZI')": 1071,
      "('41583aeef03cd201c7c8775e4113986e', 'IZXI')": 1071,
      "('41583aeef03cd201c7c8775e4113986e', 'IZYI')": 1071
    },
    "variant_shots_executed": {
      "('7a1cf0d19d9af24d16b163b3becc2b5b', 'III')": 400,
      "('7a1cf0d19d9af24d16b163b3becc2b5b', 'ZII')": 400,
      "('7a1cf0d19d9af24d16b163b3becc2b5b', 'XII')": 400,
      "('7a1cf0d19d9af24d16b163b3becc2b5b', 'YII')": 400,
      "('92a20c78bff5d88011eb51048df8311f', 'III')": 400,
      "('92a20c78bff5d88011eb51048df8311f', 'ZII')": 400,
      "('92a20c78bff5d88011eb51048df8311f', 'XII')": 400,
      "('92a20c78bff5d88011eb51048df8311f', 'YII')": 400,
      "('f2f288fe99730e84d15df38b099cd208', 'III')": 400,
      "('f2f288fe99730e84d15df38b099cd208', 'ZII')": 400,
      "('f2f288fe99730e84d15df38b099cd208', 'XII')": 400,
      "('f2f288fe99730e84d15df38b099cd208', 'YII')": 400,
      "('1011244113be3680b3d3e6b617b27dae', 'III')": 400,
      "('1011244113be3680b3d3e6b617b27dae', 'ZII')": 400,
      "('1011244113be3680b3d3e6b617b27dae', 'XII')": 400,
      "('1011244113be3680b3d3e6b617b27dae', 'YII')": 400,
      "('00cb36ab40c912315350663a5775a661', 'IZII')": 400,
      "('00cb36ab40c912315350663a5775a661', 'IZZI')": 400,
      "('00cb36ab40c912315350663a5775a661', 'IZXI')": 400,
      "('00cb36ab40c912315350663a5775a661', 'IZYI')": 400,
      "('1687d8b9ede8d7bd59c825e605d89bc1', 'IZII')": 400,
      "('1687d8b9ede8d7bd59c825e605d89bc1', 'IZZI')": 400,
      "('1687d8b9ede8d7bd59c825e605d89bc1', 'IZXI')": 400,
      "('1687d8b9ede8d7bd59c825e605d89bc1', 'IZYI')": 400,
      "('da6f6010ba2f1879dba5e0b8e9abf52c', 'IZII')": 400,
      "('da6f6010ba2f1879dba5e0b8e9abf52c', 'IZZI')": 400,
      "('da6f6010ba2f1879dba5e0b8e9abf52c', 'IZXI')": 400,
      "('da6f6010ba2f1879dba5e0b8e9abf52c', 'IZYI')": 400,
      "('41583aeef03cd201c7c8775e4113986e', 'IZII')": 400,
      "('41583aeef03cd201c7c8775e4113986e', 'IZZI')": 400,
      "('41583aeef03cd201c7c8775e4113986e', 'IZXI')": 400,
      "('41583aeef03cd201c7c8775e4113986e', 'IZYI')": 400
    },
    "variant_iterations": {
      "('7a1cf0d19d9af24d16b163b3becc2b5b', 'III')": 8,
      "('7a1cf0d19d9af24d16b163b3becc2b5b', 'ZII')": 8,
      "('7a1cf0d19d9af24d16b163b3becc2b5b', 'XII')": 8,
      "('7a1cf0d19d9af24d16b163b3becc2b5b', 'YII')": 8,
      "('92a20c78bff5d88011eb51048df8311f', 'III')": 8,
      "('92a20c78bff5d88011eb51048df8311f', 'ZII')": 8,
      "('92a20c78bff5d88011eb51048df8311f', 'XII')": 8,
      "('92a20c78bff5d88011eb51048df8311f', 'YII')": 8,
      "('f2f288fe99730e84d15df38b099cd208', 'III')": 8,
      "('f2f288fe99730e84d15df38b099cd208', 'ZII')": 8,
      "('f2f288fe99730e84d15df38b099cd208', 'XII')": 8,
      "('f2f288fe99730e84d15df38b099cd208', 'YII')": 8,
      "('1011244113be3680b3d3e6b617b27dae', 'III')": 8,
      "('1011244113be3680b3d3e6b617b27dae', 'ZII')": 8,
      "('1011244113be3680b3d3e6b617b27dae', 'XII')": 8,
      "('1011244113be3680b3d3e6b617b27dae', 'YII')": 8,
      "('00cb36ab40c912315350663a5775a661', 'IZII')": 8,
      "('00cb36ab40c912315350663a5775a661', 'IZZI')": 8,
      "('00cb36ab40c912315350663a5775a661', 'IZXI')": 8,
      "('00cb36ab40c912315350663a5775a661', 'IZYI')": 8,
      "('1687d8b9ede8d7bd59c825e605d89bc1', 'IZII')": 8,
      "('1687d8b9ede8d7bd59c825e605d89bc1', 'IZZI')": 8,
      "('1687d8b9ede8d7bd59c825e605d89bc1', 'IZXI')": 8,
      "('1687d8b9ede8d7bd59c825e605d89bc1', 'IZYI')": 8,
      "('da6f6010ba2f1879dba5e0b8e9abf52c', 'IZII')": 8,
      "('da6f6010ba2f1879dba5e0b8e9abf52c', 'IZZI')": 8,
      "('da6f6010ba2f1879dba5e0b8e9abf52c', 'IZXI')": 8,
      "('da6f6010ba2f1879dba5e0b8e9abf52c', 'IZYI')": 8,
      "('41583aeef03cd201c7c8775e4113986e', 'IZII')": 8,
      "('41583aeef03cd201c7c8775e4113986e', 'IZZI')": 8,
      "('41583aeef03cd201c7c8775e4113986e', 'IZXI')": 8,
      "('41583aeef03cd201c7c8775e4113986e', 'IZYI')": 8
    },
    "variant_stopping_info": {
      "('7a1cf0d19d9af24d16b163b3becc2b5b', 'III')": {
        "criterion": "ewma",
        "distances": [
          0.0,
          0.0,
          0.0
        ],
        "aggregate": 0.0,
        "threshold": 0.01,
        "offset": 3,
        "window": 3,
        "alpha": 0.5
      },
      "('7a1cf0d19d9af24d16b163b3becc2b5b', 'ZII')": {
        "criterion": "ewma",
        "distances": [
          0.0,
          0.0,
          0.0
        ],
        "aggregate": 0.0,
        "threshold": 0.01,
        "offset": 3,
        "window": 3,
        "alpha": 0.5
      },
      "('7a1cf0d19d9af24d16b163b3becc2b5b', 'XII')": {
        "criterion": "ewma",
        "distances": [
          0.0,
          0.0,
          0.0
        ],
        "aggregate": 0.0,
        "threshold": 0.01,
        "offset": 3,
        "window": 3,
        "alpha": 0.5
      },
      "('7a1cf0d19d9af24d16b163b3becc2b5b', 'YII')": {
        "criterion": "ewma",
        "distances": [
          0.0,
          0.0,
          0.0
        ],
        "aggregate": 0.0,
        "threshold": 0.01,
        "offset": 3,
        "window": 3,
        "alpha": 0.5
      },
      "('92a20c78bff5d88011eb51048df8311f', 'III')": {
        "criterion": "ewma",
        "distances": [
          0.0,
          0.0,
          0.0
        ],
        "aggregate": 0.0,
        "threshold": 0.01,
        "offset": 3,
        "window": 3,
        "alpha": 0.5
      },
      "('92a20c78bff5d88011eb51048df8311f', 'ZII')": {
        "criterion": "ewma",
        "distances": [
          0.0,
          0.0,
          0.0
        ],
        "aggregate": 0.0,
        "threshold": 0.01,
        "offset": 3,
        "window": 3,
        "alpha": 0.5
      },
      "('92a20c78bff5d88011eb51048df8311f', 'XII')": {
        "criterion": "ewma",
        "distances": [
          0.0,
          0.0,
          0.0
        ],
        "aggregate": 0.0,
        "threshold": 0.01,
        "offset": 3,
        "window": 3,
        "alpha": 0.5
      },
      "('92a20c78bff5d88011eb51048df8311f', 'YII')": {
        "criterion": "ewma",
        "distances": [
          0.0,
          0.0,
          0.0
        ],
        "aggregate": 0.0,
        "threshold": 0.01,
        "offset": 3,
        "window": 3,
        "alpha": 0.5
      },
      "('f2f288fe99730e84d15df38b099cd208', 'III')": {
        "criterion": "ewma",
        "distances": [
          0.0,
          0.0,
          0.0
        ],
        "aggregate": 0.0,
        "threshold": 0.01,
        "offset": 3,
        "window": 3,
        "alpha": 0.5
      },
      "('f2f288fe99730e84d15df38b099cd208', 'ZII')": {
        "criterion": "ewma",
        "distances": [
          0.0,
          0.0,
          0.0
        ],
        "aggregate": 0.0,
        "threshold": 0.01,
        "offset": 3,
        "window": 3,
        "alpha": 0.5
      },
      "('f2f288fe99730e84d15df38b099cd208', 'XII')": {
        "criterion": "ewma",
        "distances": [
          0.0,
          0.0,
          0.0
        ],
        "aggregate": 0.0,
        "threshold": 0.01,
        "offset": 3,
        "window": 3,
        "alpha": 0.5
      },
      "('f2f288fe99730e84d15df38b099cd208', 'YII')": {
        "criterion": "ewma",
        "distances": [
          0.0,
          0.0,
          0.0
        ],
        "aggregate": 0.0,
        "threshold": 0.01,
        "offset": 3,
        "window": 3,
        "alpha": 0.5
      },
      "('1011244113be3680b3d3e6b617b27dae', 'III')": {
        "criterion": "ewma",
        "distances": [
          0.0,
          0.0,
          0.0
        ],
        "aggregate": 0.0,
        "threshold": 0.01,
        "offset": 3,
        "window": 3,
        "alpha": 0.5
      },
      "('1011244113be3680b3d3e6b617b27dae', 'ZII')": {
        "criterion": "ewma",
        "distances": [
          0.0,
          0.0,
          0.0
        ],
        "aggregate": 0.0,
        "threshold": 0.01,
        "offset": 3,
        "window": 3,
        "alpha": 0.5
      },
      "('1011244113be3680b3d3e6b617b27dae', 'XII')": {
        "criterion": "ewma",
        "distances": [
          0.0,
          0.0,
          0.0
        ],
        "aggregate": 0.0,
        "threshold": 0.01,
        "offset": 3,
        "window": 3,
        "alpha": 0.5
      },
      "('1011244113be3680b3d3e6b617b27dae', 'YII')": {
        "criterion": "ewma",
        "distances": [
          0.0,
          0.0,
          0.0
        ],
        "aggregate": 0.0,
        "threshold": 0.01,
        "offset": 3,
        "window": 3,
        "alpha": 0.5
      },
      "('00cb36ab40c912315350663a5775a661', 'IZII')": {
        "criterion": "ewma",
        "distances": [
          0.0,
          0.0,
          0.0
        ],
        "aggregate": 0.0,
        "threshold": 0.01,
        "offset": 3,
        "window": 3,
        "alpha": 0.5
      },
      "('00cb36ab40c912315350663a5775a661', 'IZZI')": {
        "criterion": "ewma",
        "distances": [
          0.0,
          0.0,
          0.0
        ],
        "aggregate": 0.0,
        "threshold": 0.01,
        "offset": 3,
        "window": 3,
        "alpha": 0.5
      },
      "('00cb36ab40c912315350663a5775a661', 'IZXI')": {
        "criterion": "ewma",
        "distances": [
          0.0,
          0.0,
          0.0
        ],
        "aggregate": 0.0,
        "threshold": 0.01,
        "offset": 3,
        "window": 3,
        "alpha": 0.5
      },
      "('00cb36ab40c912315350663a5775a661', 'IZYI')": {
        "criterion": "ewma",
        "distances": [
          0.0,
          0.0,
          0.0
        ],
        "aggregate": 0.0,
        "threshold": 0.01,
        "offset": 3,
        "window": 3,
        "alpha": 0.5
      },
      "('1687d8b9ede8d7bd59c825e605d89bc1', 'IZII')": {
        "criterion": "ewma",
        "distances": [
          0.0,
          0.0,
          0.0
        ],
        "aggregate": 0.0,
        "threshold": 0.01,
        "offset": 3,
        "window": 3,
        "alpha": 0.5
      },
      "('1687d8b9ede8d7bd59c825e605d89bc1', 'IZZI')": {
        "criterion": "ewma",
        "distances": [
          0.0,
          0.0,
          0.0
        ],
        "aggregate": 0.0,
        "threshold": 0.01,
        "offset": 3,
        "window": 3,
        "alpha": 0.5
      },
      "('1687d8b9ede8d7bd59c825e605d89bc1', 'IZXI')": {
        "criterion": "ewma",
        "distances": [
          0.0,
          0.0,
          0.0
        ],
        "aggregate": 0.0,
        "threshold": 0.01,
        "offset": 3,
        "window": 3,
        "alpha": 0.5
      },
      "('1687d8b9ede8d7bd59c825e605d89bc1', 'IZYI')": {
        "criterion": "ewma",
        "distances": [
          0.0,
          0.0,
          0.0
        ],
        "aggregate": 0.0,
        "threshold": 0.01,
        "offset": 3,
        "window": 3,
        "alpha": 0.5
      },
      "('da6f6010ba2f1879dba5e0b8e9abf52c', 'IZII')": {
        "criterion": "ewma",
        "distances": [
          0.0,
          0.0,
          0.0
        ],
        "aggregate": 0.0,
        "threshold": 0.01,
        "offset": 3,
        "window": 3,
        "alpha": 0.5
      },
      "('da6f6010ba2f1879dba5e0b8e9abf52c', 'IZZI')": {
        "criterion": "ewma",
        "distances": [
          0.0,
          0.0,
          0.0
        ],
        "aggregate": 0.0,
        "threshold": 0.01,
        "offset": 3,
        "window": 3,
        "alpha": 0.5
      },
      "('da6f6010ba2f1879dba5e0b8e9abf52c', 'IZXI')": {
        "criterion": "ewma",
        "distances": [
          0.0,
          0.0,
          0.0
        ],
        "aggregate": 0.0,
        "threshold": 0.01,
        "offset": 3,
        "window": 3,
        "alpha": 0.5
      },
      "('da6f6010ba2f1879dba5e0b8e9abf52c', 'IZYI')": {
        "criterion": "ewma",
        "distances": [
          0.0,
          0.0,
          0.0
        ],
        "aggregate": 0.0,
        "threshold": 0.01,
        "offset": 3,
        "window": 3,
        "alpha": 0.5
      },
      "('41583aeef03cd201c7c8775e4113986e', 'IZII')": {
        "criterion": "ewma",
        "distances": [
          0.0,
          0.0,
          0.0
        ],
        "aggregate": 0.0,
        "threshold": 0.01,
        "offset": 3,
        "window": 3,
        "alpha": 0.5
      },
      "('41583aeef03cd201c7c8775e4113986e', 'IZZI')": {
        "criterion": "ewma",
        "distances": [
          0.0,
          0.0,
          0.0
        ],
        "aggregate": 0.0,
        "threshold": 0.01,
        "offset": 3,
        "window": 3,
        "alpha": 0.5
      },
      "('41583aeef03cd201c7c8775e4113986e', 'IZXI')": {
        "criterion": "ewma",
        "distances": [
          0.0,
          0.0,
          0.0
        ],
        "aggregate": 0.0,
        "threshold": 0.01,
        "offset": 3,
        "window": 3,
        "alpha": 0.5
      },
      "('41583aeef03cd201c7c8775e4113986e', 'IZYI')": {
        "criterion": "ewma",
        "distances": [
          0.0,
          0.0,
          0.0
        ],
        "aggregate": 0.0,
        "threshold": 0.01,
        "offset": 3,
        "window": 3,
        "alpha": 0.5
      }
    },
    "incremental": {
      "initial_batch_shots": null,
      "batch_shots": 50,
      "threshold": 0.01,
      "offset": 3,
      "stability_k": 3,
      "stopping_criterion": "ewma",
      "distance_metric": "tvd",
      "window_size": 3,
      "ewma_alpha": 0.5
    }
  },
  "absolute_error": {
    "ibm_aer": {
      "aer.fake_torino": {
        "('3364928460a7f13fdc149fc981b2a466', 'ZIIII')": 0.030400000000000073
      }
    }
  },
  "shots_executed": 12800,
  "distance_to_noisy_vanilla": 0.03813333333333335
}